gopt/__init__.py
gopt/packages/__init__.py
gopt/packages/common/__init__.py
gopt/packages/common/algo_front.py
gopt/packages/common/commons.py
gopt/packages/common/engineering_mode.py
gopt/packages/common/exception.py
gopt/packages/common/external_optimization_problem.py
gopt/packages/common/install_packages.py
gopt/packages/common/prob_front.py
gopt/packages/common/singleton.py
gopt/packages/platgo/GeneticAlgorithm.py
gopt/packages/platgo/Population.py
gopt/packages/platgo/Problem.py
gopt/packages/platgo/Track.py
gopt/packages/platgo/__init__.py
gopt/packages/platgo/algorithms/ANSGA3.py
gopt/packages/platgo/algorithms/Adam.py
gopt/packages/platgo/algorithms/BA.py
gopt/packages/platgo/algorithms/BCEIBEA.py
gopt/packages/platgo/algorithms/BCEMOEAD.py
gopt/packages/platgo/algorithms/BSO.py
gopt/packages/platgo/algorithms/CCMO.py
gopt/packages/platgo/algorithms/CMOEA_MS.py
gopt/packages/platgo/algorithms/CSO.py
gopt/packages/platgo/algorithms/C_MOEA_D.py
gopt/packages/platgo/algorithms/DE.py
gopt/packages/platgo/algorithms/EAGMOEAD.py
gopt/packages/platgo/algorithms/EA_HEX.py
gopt/packages/platgo/algorithms/EGO.py
gopt/packages/platgo/algorithms/FA.py
gopt/packages/platgo/algorithms/FEP.py
gopt/packages/platgo/algorithms/GA.py
gopt/packages/platgo/algorithms/GDE3.py
gopt/packages/platgo/algorithms/GFMMOEA.py
gopt/packages/platgo/algorithms/IBEA.py
gopt/packages/platgo/algorithms/I_DBEA.py
gopt/packages/platgo/algorithms/KnEA.py
gopt/packages/platgo/algorithms/MOCGDE.py
gopt/packages/platgo/algorithms/MOEADDU.py
gopt/packages/platgo/algorithms/MOEAD_DE.py
gopt/packages/platgo/algorithms/MOEA_TWS.py
gopt/packages/platgo/algorithms/MOPSO.py
gopt/packages/platgo/algorithms/MSEA.py
gopt/packages/platgo/algorithms/MaOEACSS.py
gopt/packages/platgo/algorithms/NNIA.py
gopt/packages/platgo/algorithms/NSGA2.py
gopt/packages/platgo/algorithms/NSGA2SDR.py
gopt/packages/platgo/algorithms/NSGA3.py
gopt/packages/platgo/algorithms/PSO.py
gopt/packages/platgo/algorithms/RVEA.py
gopt-0.0.3.dist-info/METADATA
gopt-0.0.3.dist-info/WHEEL
gopt-0.0.3.dist-info/license.txt
gopt-0.0.3.dist-info/top_level.txt
gopt-0.0.3.dist-info/RECORD
